{
  "posts": [
    {
      "id": "next.js13",
      "title": "Next.js13を学ぶ",
      "content": "How to learn Next.js13How to learn Next.js13How to learn Next.js13How to learn Next.js13How to learn Next.js13How to learn Next.js13How to learn Next.js13How to learn Next.js13How to learn Next.js13How to learn Next.js13How to learn Next.js13How to learn Next.js13How to learn Next.js13How to learn Next.js13How to learn Next.js13How to learn Next.js13",
      "createdAt": "2024/02/22"
    },
    {
      "id": "json-server",
      "title": "Json-server",
      "content": "How to install json-server",
      "createdAt": "2024/06/07"
    },
    {
      "id": "nextjs13test",
      "title": "nextjs13タイトル",
      "content": "nextjsのApprouterはデフォルトでSSRを行います。",
      "createdAt": "2025-01-03T00:51:16.579Z"
    },
    {
      "id": "test",
      "title": "test",
      "content": "test",
      "createdAt": "2025-01-03T00:54:25.130Z"
    },
    {
      "id": "sss",
      "title": "ddd",
      "content": "ffffff",
      "createdAt": "2025-01-03T01:04:00.233Z"
    },
    {
      "id": "dd",
      "title": "dd",
      "content": "dd",
      "createdAt": "2025-01-03T01:04:23.811Z"
    },
    {
      "id": "hoge",
      "title": "fuga",
      "content": "fugo",
      "createdAt": "2025-01-03T01:10:32.833Z"
    }
  ]
}